{
	"format_version": "1.12.0",
	"minecraft:geometry": [
		{
			"description": {
				"identifier": "geometry.sorter",
				"texture_width": 64,
				"texture_height": 64,
				"visible_bounds_width": 2,
				"visible_bounds_height": 2.5,
				"visible_bounds_offset": [0, 0.75, 0]
			},
			"bones": [
				{
					"name": "bone",
					"pivot": [0, 0, 0],
					"cubes": [
						{"origin": [-2, 0, -2], "size": [4, 7, 4], "uv": [0, 0]},
						{"origin": [-5, 7, -5], "size": [10, 6, 10], "uv": [0, 17]},
						{"origin": [-8, 13, -8], "size": [16, 1, 16], "uv": [0, 0]},
						{"origin": [-8, 0, 6], "size": [2, 13, 2], "uv": [44, 17]},
						{"origin": [-8, 0, -8], "size": [2, 13, 2], "uv": [36, 43]},
						{"origin": [6, 0, -8], "size": [2, 13, 2], "uv": [0, 33]},
						{"origin": [6, 0, 6], "size": [2, 13, 2], "uv": [8, 33]},
						{"origin": [-8, 14, -8], "size": [2, 2, 16], "uv": [0, 33]},
						{"origin": [6, 14, -8], "size": [2, 2, 16], "uv": [24, 17]},
						{"origin": [-6, 14, -8], "size": [12, 2, 2], "uv": [20, 39]},
						{"origin": [-6, 14, 6], "size": [12, 2, 2], "uv": [20, 35]}
					]
				}
			]
		}
	]
}